chicagorequests/__init__.py
chicagorequests/request_types.py
chicagorequests-0.0.5.dist-info/LICENSE
chicagorequests-0.0.5.dist-info/METADATA
chicagorequests-0.0.5.dist-info/WHEEL
chicagorequests-0.0.5.dist-info/entry_points.txt
chicagorequests-0.0.5.dist-info/top_level.txt
chicagorequests-0.0.5.dist-info/RECORD
