Metadata-Version: 2.1
Name: chicagorequests
Version: 0.0.5
Summary: command line tool for downloading Chicago Open311 data
Author-email: Forest Gregg <fgregg@datamade.us>
Project-URL: Homepage, https://github.com/fgregg/chicagorequests/
License-File: LICENSE
Requires-Dist: click
Requires-Dist: tqdm
Requires-Dist: scrapelib
Requires-Dist: tabulate
